pysparkformat/__init__.py
pysparkformat/http/__init__.py
pysparkformat/http/csv.py
pysparkformat/http/file.py
pysparkformat/http/json.py
pysparkformat/http/page.py
pysparkformat-0.0.13.dist-info/licenses/LICENSE
pysparkformat-0.0.13.dist-info/METADATA
pysparkformat-0.0.13.dist-info/WHEEL
pysparkformat-0.0.13.dist-info/top_level.txt
pysparkformat-0.0.13.dist-info/RECORD
