Metadata-Version: 2.4
Name: pysparkformat
Version: 0.0.13
Summary: Collection of Apache Spark Custom Data Formats
Author-email: Ilya Aniskovets <ilya@aniskovets.com>
License: Apache-2.0
Project-URL: Homepage, https://github.com/aig/pysparkformat
Project-URL: Issues, https://github.com/aig/pysparkformat/issues
Requires-Python: >=3.9
License-File: LICENSE
Requires-Dist: requests
Requires-Dist: pyarrow
Requires-Dist: pandas
Requires-Dist: grpcio
Requires-Dist: grpcio-status
Dynamic: license-file
